minillmlib/__init__.py
minillmlib/core/__init__.py
minillmlib/core/chat_node.py
minillmlib/models/__init__.py
minillmlib/models/generator_info.py
minillmlib/models/model_zoo.py
minillmlib/utils/__init__.py
minillmlib/utils/json_utils.py
minillmlib/utils/logging_utils.py
minillmlib/utils/message_utils.py
minillmlib-0.4.4.dist-info/licenses/LICENSE
minillmlib-0.4.4.dist-info/METADATA
minillmlib-0.4.4.dist-info/WHEEL
minillmlib-0.4.4.dist-info/top_level.txt
minillmlib-0.4.4.dist-info/RECORD
