Metadata-Version: 2.4
Name: minillmlib
Version: 0.4.4
Summary: Minimalist Library for programming with LLMs
Author: Quentin Feuillade--Montixi
License: MIT License
Project-URL: Homepage, https://github.com/qfeuilla/MiniLLMLib
Requires-Python: >=3.12
License-File: LICENSE
Requires-Dist: openai==1.79.0
Requires-Dist: anthropic==0.72.0
Requires-Dist: mistralai==1.7.0
Requires-Dist: requests==2.32.3
Requires-Dist: httpx==0.28.1
Requires-Dist: python-dotenv==1.1.0
Requires-Dist: json_repair==0.44.1
Requires-Dist: pydub==0.25.1
Requires-Dist: pymongo==4.13.0
Provides-Extra: huggingface
Requires-Dist: torch; extra == "huggingface"
Requires-Dist: transformers; extra == "huggingface"
Provides-Extra: dev
Requires-Dist: pytest==8.2.2; extra == "dev"
Dynamic: license-file
